drp_package/__init__.py
drp_package/data_NM.json
drp_package/data_NPP.json
drp_package/data_simulation.py
drp_package/data_transformation.py
drp_package/datamodel.txt
drp_package/DRPNgay.py
drp_package/DRPTuan.py
drp_package/new_input.json
drp_package/NM_TCO_rawdata_298.csv
drp_package/TCO_NPP_rawdata_298.csv
drp_package/test.json
drp_package/test3009_.json
drp_package-0.6.2.dist-info/METADATA
drp_package-0.6.2.dist-info/WHEEL
drp_package-0.6.2.dist-info/RECORD
