Metadata-Version: 2.1
Name: drp_package
Version: 0.6.2
Summary: 
Author: Your Name
Author-email: you@example.com
Requires-Python: >=3.9,<4.0
Classifier: Programming Language :: Python :: 3
Classifier: Programming Language :: Python :: 3.9
Classifier: Programming Language :: Python :: 3.10
Classifier: Programming Language :: Python :: 3.11
Requires-Dist: matplotlib (==3.7.1)
Requires-Dist: numpy (>=1.13.3)
Requires-Dist: ortools (==9.7.2996)
